README.md
setup.py
ip_city_handler/__init__.py
ip_city_handler/constents.py
ip_city_handler/data.py
ip_city_handler/exception.py
ip_city_handler/handler.py
ip_city_handler/parser.py
ip_city_handler.egg-info/PKG-INFO
ip_city_handler.egg-info/SOURCES.txt
ip_city_handler.egg-info/dependency_links.txt
ip_city_handler.egg-info/top_level.txt